{"name":"in the making...","device":1,"model":5,"type":"light","data":{"type":2,"staticEffect":"[\"#ff0099\",\"#ff0099\",\"#ff0099\",\"#ff0099\",\"#00ccff\",\"#00ccff\",\"#99ff00\",\"#99ff00\",\"#99ff00\",\"#ff2020\",\"#ff2020\",\"#ff2020\",\"#ff9800\",\"#ff9800\",\"#ff0099\",\"#ff0099\",\"#00ccff\",\"#00ccff\",\"#00ccff\",\"#99ff00\",\"#99ff00\",\"#99ff00\",\"#ff2020\",\"#ff2020\",\"#ff2020\",\"#ff2020\",\"#ff9800\",\"#ff9800\",\"#ff0099\",\"#ff0099\",\"#00ccff\",\"#00ccff\",\"#00ccff\",\"#99ff00\",\"#99ff00\",\"#99ff00\",\"#ff2020\",\"#ff2020\",\"#ff2020\",\"#ff9800\",\"#ff9800\",\"#ff0099\",\"#ff0099\",\"#00ccff\",\"#00ccff\",\"#00ccff\",\"#99ff00\",\"#99ff00\",\"#99ff00\",\"#ff2020\",\"#ff2020\",\"#ff9800\",\"#ff9800\",\"#ff0099\",\"#ff0099\",\"#00ccff\",\"#00ccff\",\"#ff2020\",\"#ff2020\",\"#ff9800\",\"#ff9800\"]","dynamicEffect":"[\"#ff0000\",\"#ff8000\",\"#ffff00\",\"#80ff00\",\"#00ff00\",\"#00ff80\",\"#00ffff\",\"#0080ff\",\"#0000ff\",\"#8000ff\",\"#ff00ff\",\"#ff0080\"]"},"crc":"2ffa2142"}